{"char-ai":[{"ccid":1,"cardId":"card-ai-03-schl-00","nameJa":"嘘から出た実"},{"ccid":2,"cardId":"card-ai-04-casl-00","nameJa":"ごほうび発見"},{"ccid":3,"cardId":"card-ai-05-idol-00","nameJa":"掴みとる夢"},{"ccid":4,"cardId":"card-ai-05-kait-00","nameJa":"私にとって大切な曲"},{"ccid":5,"cardId":"card-ai-05-vlnt-00","nameJa":"ちょこ～っとバレンタイン"},{"ccid":6,"cardId":"card-ai-05-tact-00","nameJa":"セクシーシューティング"},{"ccid":7,"cardId":"card-ai-05-mizg-01","nameJa":"ネオン煌めくナイトプール"},{"ccid":8,"cardId":"card-ai-02-eve-00","nameJa":"初日に誓う今年の飛躍"},{"ccid":9,"cardId":"card-ai-05-rock-00","nameJa":"クールにキメるぼっち収録"},{"ccid":10,"cardId":"card-ai-02-eve-01","nameJa":"えんそう！大成功"},{"ccid":11,"cardId":"card-ai-05-fest-00","nameJa":"火花散らす熱いキモチ"},{"ccid":12,"cardId":"card-ai-05-miku-01","nameJa":"鳴り止まないアンコール"},{"ccid":13,"cardId":"card-ai-05-birt-00","nameJa":"愛されラーメンバースデー"},{"ccid":14,"cardId":"card-ai-05-mizg-02","nameJa":"スプラッシュ・シーサイド"}],"char-aoi":[{"ccid":1,"cardId":"card-aoi-03-schl-00","nameJa":"ホームグラウンド"},{"ccid":2,"cardId":"card-aoi-04-casl-00","nameJa":"冷めた夜"},{"ccid":3,"cardId":"card-aoi-05-idol-00","nameJa":"濡れた髪は何を語る"},{"ccid":4,"cardId":"card-aoi-05-kait-00","nameJa":"growing up！"},{"ccid":5,"cardId":"card-aoi-05-vlnt-00","nameJa":"おかしな気分は君のせい"},{"ccid":6,"cardId":"card-aoi-05-mizg-01","nameJa":"君と結ぶ夏の約束"},{"ccid":7,"cardId":"card-aoi-02-eve-01","nameJa":"そっとしておく仲間の背中"},{"ccid":8,"cardId":"card-aoi-05-fest-00","nameJa":"名残の空に約束を"},{"ccid":9,"cardId":"card-aoi-05-wedd-00","nameJa":"リングに誓う永遠"},{"ccid":10,"cardId":"card-aoi-05-circ-00","nameJa":"ダーティーアクセル"},{"ccid":11,"cardId":"card-aoi-05-miku-01","nameJa":"分かち合う最高の時間"},{"ccid":12,"cardId":"card-aoi-02-eve-02","nameJa":"熱情クールダウン"}],"char-chs":[{"ccid":1,"cardId":"card-chs-03-schl-00","nameJa":"課題クリア！"},{"ccid":2,"cardId":"card-chs-04-casl-00","nameJa":"昼下がりのお買いもの"},{"ccid":3,"cardId":"card-chs-05-idol-00","nameJa":"照度を増す自信"},{"ccid":4,"cardId":"card-chs-05-seik-00","nameJa":"一夜限りの聖なるステージ"},{"ccid":5,"cardId":"card-chs-02-eve-01","nameJa":"賑やかなお正月"},{"ccid":6,"cardId":"card-chs-05-rock-00","nameJa":"ひと握りの勇気"},{"ccid":7,"cardId":"card-chs-05-chsk-00","nameJa":"絆溢れるクリエーション"},{"ccid":8,"cardId":"card-chs-05-flow-00","nameJa":"檻に咲く名花"},{"ccid":9,"cardId":"card-chs-05-pajm-00","nameJa":"お姫様抱っこで夢の中"},{"ccid":10,"cardId":"card-chs-05-yukt-00","nameJa":"祭りに光る一番星"},{"ccid":11,"cardId":"card-chs-05-birt-00","nameJa":"心届けるバースデー"},{"ccid":12,"cardId":"card-chs-05-chia-00","nameJa":"燃える頬と熱い心"}],"char-hrk":[{"ccid":5,"cardId":"card-hrk-02-eve-01","nameJa":"図らずもバースデーライブ"},{"ccid":1,"cardId":"card-hrk-03-schl-00","nameJa":"後輩思いのお姉さん"},{"ccid":2,"cardId":"card-hrk-04-casl-00","nameJa":"全力タイムセール"},{"ccid":3,"cardId":"card-hrk-05-idol-00","nameJa":"とても頼れるお姉さん"},{"ccid":4,"cardId":"card-hrk-05-mizg-01","nameJa":"恵みのサニーシャワー"},{"ccid":6,"cardId":"card-hrk-05-xmas-00","nameJa":"二人きり、冬夜の打ち上げ"},{"ccid":7,"cardId":"card-hrk-05-chna-00","nameJa":"解き放たれる十七歳"},{"ccid":8,"cardId":"card-hrk-05-idol-03","nameJa":"私、決めたよ"},{"ccid":9,"cardId":"card-hrk-05-onep-00","nameJa":"ゆるり妄想温泉の旅"},{"ccid":10,"cardId":"card-hrk-05-sail-00","nameJa":"陽光見守るとなりの青春"},{"ccid":11,"cardId":"card-hrk-02-eve-03","nameJa":"巡る季節と色褪せない日々"},{"ccid":12,"cardId":"card-hrk-05-fest-00","nameJa":"共に繋いだ約束の音"},{"ccid":13,"cardId":"card-hrk-05-pair-00","nameJa":"膨らむ頬と未来への期待"},{"ccid":14,"cardId":"card-hrk-05-birt-00","nameJa":"大人のキャンプバースデー"},{"ccid":15,"cardId":"card-hrk-05-pajm-00","nameJa":"私の理想のデートプラン"}],"char-kkr":[{"ccid":1,"cardId":"card-kkr-03-schl-00","nameJa":"たまには本気で"},{"ccid":2,"cardId":"card-kkr-04-casl-00","nameJa":"無邪気ないたずらっ子"},{"ccid":3,"cardId":"card-kkr-05-idol-00","nameJa":"新生リズノワの誇り"},{"ccid":4,"cardId":"card-kkr-05-seik-00","nameJa":"私は私"},{"ccid":5,"cardId":"card-kkr-05-vlnt-00","nameJa":"ビタースイートメモリーズ"},{"ccid":6,"cardId":"card-kkr-05-mizg-01","nameJa":"忘れられない夏の味"},{"ccid":7,"cardId":"card-kkr-05-newy-00","nameJa":"うれしはずかし初詣"},{"ccid":8,"cardId":"card-kkr-02-eve-00","nameJa":"こころのカワイイTV"},{"ccid":9,"cardId":"card-kkr-05-kion-00","nameJa":"打ち上げティータイム"},{"ccid":10,"cardId":"card-kkr-05-fest-00","nameJa":"戯言に隠すホントの願い"},{"ccid":11,"cardId":"card-kkr-05-birt-00","nameJa":"可愛くイタズラバースデー"},{"ccid":12,"cardId":"card-kkr-05-miku-01","nameJa":"心震える熱き想い"},{"ccid":13,"cardId":"card-kkr-05-mizg-02","nameJa":"出航！ユニコーンちゃん"}],"char-ktn":[{"ccid":1,"cardId":"card-ktn-02-casl-00","nameJa":"出発の時"},{"ccid":2,"cardId":"card-ktn-03-schl-00","nameJa":"見なれた光景"},{"ccid":3,"cardId":"card-ktn-04-casl-00","nameJa":"センチメンタルな午後"},{"ccid":4,"cardId":"card-ktn-05-idol-00","nameJa":"イノセントステージ"},{"ccid":5,"cardId":"card-ktn-05-mizg-01","nameJa":"はにかみサマームーン"},{"ccid":6,"cardId":"card-ktn-05-fest-00","nameJa":"光華霜夜"},{"ccid":7,"cardId":"card-ktn-02-eve-01","nameJa":"誰にも負けないくらい好き"},{"ccid":8,"cardId":"card-ktn-05-wedd-00","nameJa":"Perfect Bride"},{"ccid":9,"cardId":"card-ktn-05-kiok-00","nameJa":"泡沫の悲しみ、思いは胸に"},{"ccid":10,"cardId":"card-ktn-05-add-00","nameJa":"星海に捧ぐ追想の歌"},{"ccid":11,"cardId":"card-ktn-02-eve-02","nameJa":"月ストサンタからの贈り物"},{"ccid":12,"cardId":"card-ktn-05-fest-01","nameJa":"月光惑う光耀の幻影"},{"ccid":13,"cardId":"card-ktn-05-prem-00","nameJa":"リーダー達のレアショット"},{"ccid":14,"cardId":"card-ktn-05-circ-00","nameJa":"カットバックタンデム"},{"ccid":15,"cardId":"card-ktn-05-birt-00","nameJa":"雪よ降れ降れバースデー"},{"ccid":16,"cardId":"card-ktn-05-newy-00","nameJa":"新年祝う雪月花"}],"char-mei":[{"ccid":1,"cardId":"card-mei-03-schl-00","nameJa":"バランス感覚UP"},{"ccid":2,"cardId":"card-mei-04-casl-00","nameJa":"メイクアップタ～イム"},{"ccid":3,"cardId":"card-mei-05-idol-00","nameJa":"カメラ越しの笑顔"},{"ccid":4,"cardId":"card-mei-05-mizg-01","nameJa":"二人きりのサンセットビーチ"},{"ccid":5,"cardId":"card-mei-05-rock-00","nameJa":"いつかまた一緒に"},{"ccid":6,"cardId":"card-mei-05-fest-00","nameJa":"一人のアイドルとの出会い"},{"ccid":7,"cardId":"card-mei-05-mizg-02","nameJa":"隠しきれない顔の火照り"},{"ccid":8,"cardId":"card-mei-02-eve-01","nameJa":"距離が縮まる露天風呂"},{"ccid":9,"cardId":"card-mei-05-xmas-00","nameJa":"幸せ招く芽衣サンタ"},{"ccid":10,"cardId":"card-mei-05-wedd-00","nameJa":"パールホワイトの想い出"},{"ccid":11,"cardId":"card-mei-05-birt-00","nameJa":"ドーナツ山盛りバースデー"},{"ccid":12,"cardId":"card-mei-05-pair-00","nameJa":"ニャンたすてぃっくガール"},{"ccid":13,"cardId":"card-mei-05-prem-00","nameJa":"天使の囁き、悪魔の誘惑"}],"char-mna":[{"ccid":1,"cardId":"card-mna-05-idol-00","nameJa":"You're my everything"},{"ccid":2,"cardId":"card-mna-05-fest-00","nameJa":"ただ、手を繋ぐだけ"},{"ccid":3,"cardId":"card-mna-05-prem-00","nameJa":"花火に鼓動が高鳴る夜"},{"ccid":4,"cardId":"card-mna-05-vlnt-00","nameJa":"胸に残るショコラの約束"},{"ccid":5,"cardId":"card-mna-05-prem-01","nameJa":"彼女にかかる花霞"},{"ccid":6,"cardId":"card-mna-05-fest-01","nameJa":"友と集めた音の欠片"},{"ccid":7,"cardId":"card-mna-02-eve-01","nameJa":"remember shiny days"},{"ccid":8,"cardId":"card-mna-05-fest-02","nameJa":"未来願う真紅の花"},{"ccid":9,"cardId":"card-mna-05-prem-02","nameJa":"回り巡る淡い日々"}],"char-ngs":[{"ccid":1,"cardId":"card-ngs-03-schl-00","nameJa":"背中を追って"},{"ccid":2,"cardId":"card-ngs-04-casl-00","nameJa":"おひさまダイアリー"},{"ccid":3,"cardId":"card-ngs-05-idol-00","nameJa":"背中をあずけて"},{"ccid":4,"cardId":"card-ngs-05-mizg-01","nameJa":"光踊る砂浜のメッセージ"},{"ccid":5,"cardId":"card-ngs-05-flow-00","nameJa":"この瞬間の主役"},{"ccid":6,"cardId":"card-ngs-05-akma-00","nameJa":"いたずら好きな小悪魔"},{"ccid":7,"cardId":"card-ngs-02-eve-01","nameJa":"姉妹の活躍に染められて"},{"ccid":8,"cardId":"card-ngs-05-mizg-02","nameJa":"夏空シェイプアップ"},{"ccid":9,"cardId":"card-ngs-05-xmas-00","nameJa":"夢抱くクリスマスデート"},{"ccid":10,"cardId":"card-ngs-05-birt-00","nameJa":"琴乃ひゃんとバースデー"},{"ccid":11,"cardId":"card-ngs-05-yukt-00","nameJa":"日差しに火照る頬"},{"ccid":12,"cardId":"card-ngs-05-casl-02","nameJa":"もしも幼なじみと恋をしたら"},{"ccid":13,"cardId":"card-ngs-05-prem-00","nameJa":"負けない輝き"}],"char-rei":[{"ccid":1,"cardId":"card-rei-03-schl-00","nameJa":"夜の自主トレ"},{"ccid":2,"cardId":"card-rei-04-casl-00","nameJa":"密かなお楽しみ"},{"ccid":3,"cardId":"card-rei-05-idol-00","nameJa":"高台をかける薫風"},{"ccid":4,"cardId":"card-rei-05-rock-00","nameJa":"失敗なんて恐れない"},{"ccid":5,"cardId":"card-rei-02-eve-01","nameJa":"ココロ Distance"},{"ccid":6,"cardId":"card-rei-05-newy-00","nameJa":"絶対秘密のバックステージ"},{"ccid":7,"cardId":"card-rei-05-onep-00","nameJa":"花あかり誘う笑顔"},{"ccid":8,"cardId":"card-rei-05-mizg-02","nameJa":"大胆なのは夏のせい"},{"ccid":9,"cardId":"card-rei-05-fest-00","nameJa":"踊る彼女に息をのむ"},{"ccid":10,"cardId":"card-rei-05-casl-02","nameJa":"もしも君の手に触れたら"},{"ccid":11,"cardId":"card-rei-05-pair-00","nameJa":"ステップアップ・バンビーナ"},{"ccid":12,"cardId":"card-rei-02-sush-00","nameJa":"サンシャイン！！"},{"ccid":13,"cardId":"card-rei-05-birt-00","nameJa":"わくわく遊園地バースデー"},{"ccid":14,"cardId":"card-rei-05-chia-00","nameJa":"ダンシングキューピッド"}],"char-rio":[{"ccid":1,"cardId":"card-rio-01-casl-00","nameJa":"雨の中の帰路"},{"ccid":5,"cardId":"card-rio-02-eve-01","nameJa":"心引き締まるレッスン合宿"},{"ccid":2,"cardId":"card-rio-03-schl-00","nameJa":"折れない心"},{"ccid":3,"cardId":"card-rio-04-casl-00","nameJa":"スイーツライフ"},{"ccid":6,"cardId":"card-rio-05-halw-00","nameJa":"その魅力、モンスター級"},{"ccid":4,"cardId":"card-rio-05-idol-00","nameJa":"空気を震わせて"},{"ccid":7,"cardId":"card-rio-05-fest-00","nameJa":"奇跡より必然"},{"ccid":8,"cardId":"card-rio-02-eve-02","nameJa":"緊張の一瞬"},{"ccid":9,"cardId":"card-rio-05-kait-00","nameJa":"憧憬のアクター"},{"ccid":10,"cardId":"card-rio-02-eve-03","nameJa":"どたばたバカンス"},{"ccid":11,"cardId":"card-rio-05-kiok-00","nameJa":"心に刻む星月夜"},{"ccid":12,"cardId":"card-rio-05-newy-00","nameJa":"貴方と新春ホームカミング"},{"ccid":13,"cardId":"card-rio-05-wedd-00","nameJa":"ベールに隠した本音"},{"ccid":14,"cardId":"card-rio-05-birt-00","nameJa":"真心パンケーキバースデー"},{"ccid":15,"cardId":"card-rio-05-fest-01","nameJa":"過去超えし真白の花"},{"ccid":16,"cardId":"card-rio-02-miku-01","nameJa":"リズノワin北海道！"},{"ccid":17,"cardId":"card-rio-05-mizg-02","nameJa":"恥じらいのプールサイド"}],"char-rui":[{"ccid":1,"cardId":"card-rui-01-casl-00","nameJa":"夕暮れのホームで"},{"ccid":2,"cardId":"card-rui-03-schl-00","nameJa":"秘密会議"},{"ccid":3,"cardId":"card-rui-04-casl-00","nameJa":"ほっと帰り道"},{"ccid":4,"cardId":"card-rui-05-idol-00","nameJa":"ありのままの姿で"},{"ccid":5,"cardId":"card-rui-05-mizg-01","nameJa":"真夏の恥じらいショット"},{"ccid":6,"cardId":"card-rui-05-xmas-00","nameJa":"白息はずむホーリーナイト"},{"ccid":7,"cardId":"card-rui-02-eve-01","nameJa":"対等な関係"},{"ccid":8,"cardId":"card-rui-05-date-00","nameJa":"緑風誘うデートスポット"},{"ccid":9,"cardId":"card-rui-05-miku-00","nameJa":"歌に乗せて届ける想い"},{"ccid":10,"cardId":"card-rui-05-vlnt-00","nameJa":"薔薇色の夕暮れに染まって"},{"ccid":11,"cardId":"card-rui-02-eve-02","nameJa":"アシスタントの瑠依さん"},{"ccid":12,"cardId":"card-rui-05-prem-00","nameJa":"水玉を弾く白い翼"},{"ccid":13,"cardId":"card-rui-05-idol-04","nameJa":"湯けむり上る決意の朝"},{"ccid":14,"cardId":"card-rui-05-birt-00","nameJa":"満喫放課後バースデー"},{"ccid":15,"cardId":"card-rui-05-fest-01","nameJa":"空駆ける絆の翼"}],"char-ski":[{"ccid":4,"cardId":"card-ski-02-mizg-01","nameJa":"夏の夜に輝く星"},{"ccid":1,"cardId":"card-ski-03-schl-00","nameJa":"早朝猛特訓"},{"ccid":2,"cardId":"card-ski-04-casl-00","nameJa":"もふもふショッピング"},{"ccid":3,"cardId":"card-ski-05-idol-00","nameJa":"手を取り合って"},{"ccid":5,"cardId":"card-ski-05-kifj-00","nameJa":"涙のカーテンコール"},{"ccid":6,"cardId":"card-ski-05-waso-00","nameJa":"胸に秘めていた情熱"},{"ccid":7,"cardId":"card-ski-05-chsk-00","nameJa":"絆深まる姉妹のステージ"},{"ccid":8,"cardId":"card-ski-05-mizg-02","nameJa":"サンライト照らす眼差し"},{"ccid":9,"cardId":"card-ski-05-xmas-00","nameJa":"記憶から拾うスノードーム"},{"ccid":10,"cardId":"card-ski-05-poli-00","nameJa":"厳然たるプライド"},{"ccid":11,"cardId":"card-ski-05-birt-00","nameJa":"想い繋がるバースデー"},{"ccid":12,"cardId":"card-ski-05-newy-00","nameJa":"飛躍を願う新春"}],"char-skr":[{"ccid":1,"cardId":"card-skr-02-casl-00","nameJa":"夜空に咲く花"},{"ccid":2,"cardId":"card-skr-03-schl-00","nameJa":"元気100倍！"},{"ccid":3,"cardId":"card-skr-04-casl-00","nameJa":"ジューシーランチ"},{"ccid":5,"cardId":"card-skr-05-fest-00","nameJa":"あなたの光になれるように"},{"ccid":4,"cardId":"card-skr-05-idol-00","nameJa":"夢の共演"},{"ccid":6,"cardId":"card-skr-05-newy-00","nameJa":"笑う門には福来るだよ！"},{"ccid":7,"cardId":"card-skr-05-idol-03","nameJa":"この指とーまれ！"},{"ccid":8,"cardId":"card-skr-02-eve-01","nameJa":"仲良しアピール"},{"ccid":9,"cardId":"card-skr-05-chna-00","nameJa":"パクパク満腹笑顔"},{"ccid":10,"cardId":"card-skr-05-fest-01","nameJa":"太陽は光耀と共に"},{"ccid":11,"cardId":"card-skr-02-eve-02","nameJa":"あなたに贈る感謝の花束"},{"ccid":12,"cardId":"card-skr-05-sail-00","nameJa":"Happyサニーパレード"},{"ccid":13,"cardId":"card-skr-05-chia-00","nameJa":"スマイル・コネクト！"},{"ccid":14,"cardId":"card-skr-05-birt-00","nameJa":"感謝伝えるバースデー"}],"char-smr":[{"ccid":1,"cardId":"card-smr-03-schl-00","nameJa":"努力のたまもの"},{"ccid":2,"cardId":"card-smr-04-casl-00","nameJa":"ギリギリセーフ"},{"ccid":3,"cardId":"card-smr-05-idol-00","nameJa":"小さなヒロイン"},{"ccid":4,"cardId":"card-smr-05-mizg-01","nameJa":"常夏ウォーターパーク"},{"ccid":5,"cardId":"card-smr-05-xmas-00","nameJa":"六花イルミネーション"},{"ccid":6,"cardId":"card-smr-05-frut-00","nameJa":"Little lover"},{"ccid":7,"cardId":"card-smr-05-fest-00","nameJa":"歌詠み花"},{"ccid":8,"cardId":"card-smr-02-eve-00","nameJa":"憧れのスクールラブ"},{"ccid":9,"cardId":"card-smr-05-pajm-00","nameJa":"夢の国へ誘う安眠膝枕"},{"ccid":10,"cardId":"card-smr-05-mizg-02","nameJa":"波打ち際のしろくまサマー"},{"ccid":11,"cardId":"card-smr-02-eve-02","nameJa":"ほっと一息故郷の湯"},{"ccid":12,"cardId":"card-smr-05-idol-04","nameJa":"飛び立つための羽休め"},{"ccid":13,"cardId":"card-smr-05-maid-00","nameJa":"花開く名演技"},{"ccid":14,"cardId":"card-smr-05-birt-00","nameJa":"幸せおしるこバースデー"}],"char-suz":[{"ccid":1,"cardId":"card-suz-03-schl-00","nameJa":"へろへろランニング"},{"ccid":2,"cardId":"card-suz-04-casl-00","nameJa":"わくわくクッキング"},{"ccid":3,"cardId":"card-suz-05-idol-00","nameJa":"パワフルガール"},{"ccid":4,"cardId":"card-suz-05-mizg-01","nameJa":"ほろにがサマーメモリーズ"},{"ccid":5,"cardId":"card-suz-05-anml-00","nameJa":"撮れ高たっぷりショット"},{"ccid":6,"cardId":"card-suz-02-eve-01","nameJa":"期待で胸いっぱい"},{"ccid":7,"cardId":"card-suz-05-onep-00","nameJa":"背伸びをしても、届かない"},{"ccid":8,"cardId":"card-suz-05-seik-00","nameJa":"乙女のメソッド"},{"ccid":9,"cardId":"card-suz-05-xmas-00","nameJa":"恵みを運ぶアイドルサンタ"},{"ccid":10,"cardId":"card-suz-05-kion-00","nameJa":"にゃんて素晴らしい放課後！"},{"ccid":11,"cardId":"card-suz-05-birt-00","nameJa":"すずにゃん様のバースデー"},{"ccid":12,"cardId":"card-suz-05-pair-00","nameJa":"ごきげんワンぱくガール"},{"ccid":13,"cardId":"card-suz-02-eve-02","nameJa":"おせちにもスパイスを！"},{"ccid":14,"cardId":"card-suz-05-angl-00","nameJa":"天使の怠惰な午後"}],"char-szk":[{"ccid":4,"cardId":"card-szk-02-mizg-01","nameJa":"ぷかぷかリゾート"},{"ccid":1,"cardId":"card-szk-03-schl-00","nameJa":"つかの間の休息"},{"ccid":2,"cardId":"card-szk-04-casl-00","nameJa":"潜入、ドームツアー"},{"ccid":3,"cardId":"card-szk-05-idol-00","nameJa":"光の波"},{"ccid":5,"cardId":"card-szk-05-chna-00","nameJa":"夢は、きっと叶う"},{"ccid":6,"cardId":"card-szk-05-yuru-00","nameJa":"一緒に歌える幸せ"},{"ccid":7,"cardId":"card-szk-02-eve-01","nameJa":"みんなのピースを"},{"ccid":8,"cardId":"card-szk-05-rock-00","nameJa":"香るミステリアルクール"},{"ccid":9,"cardId":"card-szk-05-prem-00","nameJa":"a.k.a.サニポップ"},{"ccid":10,"cardId":"card-szk-05-pajm-00","nameJa":"万歳オフショ夢空間"},{"ccid":11,"cardId":"card-szk-05-yukt-00","nameJa":"大輪彩る夏夜の一瞬"},{"ccid":12,"cardId":"card-szk-05-birt-00","nameJa":"全開！推し活バースデー"},{"ccid":13,"cardId":"card-szk-05-sail-00","nameJa":"夢のアングラークイーン"},{"ccid":14,"cardId":"card-szk-02-eve-03","nameJa":"みんなの願いを叶えるツアー！"}],"char-yu":[{"ccid":1,"cardId":"card-yu-03-schl-00","nameJa":"自主トレ日和"},{"ccid":2,"cardId":"card-yu-04-casl-00","nameJa":"至福の時間"},{"ccid":3,"cardId":"card-yu-05-idol-00","nameJa":"白の衝撃"},{"ccid":4,"cardId":"card-yu-05-mizg-01","nameJa":"秘密のフォトセッション"},{"ccid":5,"cardId":"card-yu-05-xmas-00","nameJa":"うちらのクリスマスイブ"},{"ccid":6,"cardId":"card-yu-05-wedd-01","nameJa":"心恋、京ツアー"},{"ccid":7,"cardId":"card-yu-02-miku-00","nameJa":"セレブレイトサウンド"},{"ccid":8,"cardId":"card-yu-05-fest-00","nameJa":"甘えん坊の鈴村さん"},{"ccid":9,"cardId":"card-yu-05-vlnt-00","nameJa":"思わせぶりな戦略家"},{"ccid":10,"cardId":"card-yu-05-mizg-02","nameJa":"陽に溶けるブレークタイム"},{"ccid":11,"cardId":"card-yu-05-idol-04","nameJa":"鴨川ロマンス"},{"ccid":12,"cardId":"card-yu-05-birt-00","nameJa":"一緒にオタ活バースデー"},{"ccid":13,"cardId":"card-yu-05-fest-01","nameJa":"君と広げた絆の翼"}],"char-kan":[{"ccid":1,"cardId":"card-kan-05-idol-00","nameJa":"a piece of cake"},{"ccid":2,"cardId":"card-kan-05-poli-00","nameJa":"超強いんだから"},{"ccid":3,"cardId":"card-kan-05-idol-03","nameJa":"本音イミテーション"},{"ccid":4,"cardId":"card-kan-02-eve-01","nameJa":"kanaちゃんジャッジメント"},{"ccid":5,"cardId":"card-kan-05-chna-00","nameJa":"主役はkanaかな？"},{"ccid":6,"cardId":"card-kan-05-buny-00","nameJa":"バズらせバニー"},{"ccid":7,"cardId":"card-kan-05-birt-00","nameJa":"スリクス仲良しバースデー"}],"char-kor":[{"ccid":1,"cardId":"card-kor-05-idol-00","nameJa":"snake in the grass"},{"ccid":2,"cardId":"card-kor-05-poli-00","nameJa":"壁越しに香るゆず湯"},{"ccid":3,"cardId":"card-kor-05-idol-03","nameJa":"俊傑は我が道を貫く"},{"ccid":4,"cardId":"card-kor-05-mizg-01","nameJa":"真夏のレーベン"},{"ccid":5,"cardId":"card-kor-05-xmas-00","nameJa":"スイートラグジュアリー"},{"ccid":6,"cardId":"card-kor-05-buny-00","nameJa":"逆転のジーニアスラビット"}],"char-mhk":[{"ccid":1,"cardId":"card-mhk-05-idol-00","nameJa":"make a comeback"},{"ccid":2,"cardId":"card-mhk-05-poli-00","nameJa":"湯けむりショートトリップ"},{"ccid":3,"cardId":"card-mhk-05-idol-03","nameJa":"囚われの執心"},{"ccid":4,"cardId":"card-mhk-05-mizg-01","nameJa":"波間に揺れるノスタルジー"},{"ccid":5,"cardId":"card-mhk-02-eve-01","nameJa":"孤高の理解者"},{"ccid":6,"cardId":"card-mhk-05-xmas-00","nameJa":"一瞬の雪解け"},{"ccid":7,"cardId":"card-mhk-05-birt-00","nameJa":"浮かぶ追憶バースデー"},{"ccid":8,"cardId":"card-mhk-02-eve-02","nameJa":"獅子達のベガス征服"}],"char-mku":[{"ccid":1,"cardId":"card-mku-05-miku-00","nameJa":"世界繋ぐ未来の音"}],"char-chk":[{"ccid":1,"cardId":"card-chk-05-sush-00","nameJa":"太陽みたいに輝く笑顔で"}],"char-rik":[{"ccid":1,"cardId":"card-rik-05-sush-00","nameJa":"同志の熱さ"}],"char-yo":[{"ccid":1,"cardId":"card-yo-05-sush-00","nameJa":"実は似た者同士"}],"char-ymk":[{"ccid":1,"cardId":"card-ymk-05-miku-01","nameJa":"雪と花と奇跡の結晶"}]}